sentiment_analysis/__init__.py
sentiment_analysis/sentiment_analysis_multimodel.py
sentiment_analysis/sentiment_analysis_xlmrobertabase.py
sentiment_analysis/api/api_multimodel.py
sentiment_analysis/api/api_xlmrobertabase.py
sentiment_analysis/tests/__init__.py
sentiment_analysis/tests/clustered_news_item_list.json
sentiment_analysis/tests/conftest.py
sentiment_analysis/tests/news_item_list.json
sentiment_analysis/tests/test_analysis.py
taranis_sentiment_analysis-1.2.0.dist-info/LICENSE.md
taranis_sentiment_analysis-1.2.0.dist-info/METADATA
taranis_sentiment_analysis-1.2.0.dist-info/WHEEL
taranis_sentiment_analysis-1.2.0.dist-info/top_level.txt
taranis_sentiment_analysis-1.2.0.dist-info/RECORD
