Metadata-Version: 2.1
Name: taranis_sentiment_analysis
Version: 1.2.0
Summary: Sentiment analysis Bot for Taranis AI
Maintainer-email: AIT <benjamin.akhras@ait.ac.at>
License: EUROPEAN UNION PUBLIC LICENCE v. 1.2
Project-URL: Source Code, https://github.com/taranis-ai/sentiment-analysis
Classifier: Programming Language :: Python
Classifier: Programming Language :: Python :: 3
Classifier: Programming Language :: Python :: 3.11
Classifier: Programming Language :: Python :: 3.12
Classifier: Topic :: Security
Requires-Python: >=3.10
License-File: LICENSE.md
Requires-Dist: networkx
Provides-Extra: dev
Requires-Dist: pytest; extra == "dev"
Requires-Dist: ruff; extra == "dev"
